CHANGES.txt
LICENSE.txt
MANIFEST.in
README.txt
setup.py
src/j01/__init__.py
src/j01.autosuggest.egg-info/PKG-INFO
src/j01.autosuggest.egg-info/SOURCES.txt
src/j01.autosuggest.egg-info/dependency_links.txt
src/j01.autosuggest.egg-info/namespace_packages.txt
src/j01.autosuggest.egg-info/not-zip-safe
src/j01.autosuggest.egg-info/requires.txt
src/j01.autosuggest.egg-info/top_level.txt
src/j01/autosuggest/README.txt
src/j01/autosuggest/README_MIGRATION_P2P3.py
src/j01/autosuggest/__init__.py
src/j01/autosuggest/browser.zcml
src/j01/autosuggest/configure.zcml
src/j01/autosuggest/interfaces.py
src/j01/autosuggest/jsonrpc.py
src/j01/autosuggest/jsonrpc.zcml
src/j01/autosuggest/tests.py
src/j01/autosuggest/widget.py
src/j01/autosuggest/widget_input.pt
src/j01/autosuggest/css/j01.autosuggest.css
src/j01/autosuggest/js/j01.autosuggest.js